ffmpegcv/__init__.py
ffmpegcv/ffmpeg_noblock.py
ffmpegcv/ffmpeg_reader.py
ffmpegcv/ffmpeg_reader_camera.py
ffmpegcv/ffmpeg_reader_cuda.py
ffmpegcv/ffmpeg_reader_noblock.py
ffmpegcv/ffmpeg_reader_pannels.py
ffmpegcv/ffmpeg_reader_qsv.py
ffmpegcv/ffmpeg_reader_stream.py
ffmpegcv/ffmpeg_reader_stream_realtime.py
ffmpegcv/ffmpeg_writer.py
ffmpegcv/ffmpeg_writer_noblock.py
ffmpegcv/ffmpeg_writer_qsv.py
ffmpegcv/ffmpeg_writer_stream_realtime.py
ffmpegcv/stream_info.py
ffmpegcv/version.py
ffmpegcv/video_info.py
ffmpegcv-0.3.17.dist-info/METADATA
ffmpegcv-0.3.17.dist-info/WHEEL
ffmpegcv-0.3.17.dist-info/top_level.txt
ffmpegcv-0.3.17.dist-info/RECORD
