Metadata-Version: 2.4
Name: ffmpegcv
Version: 0.3.17
Home-page: https://github.com/chenxinfeng4/ffmpegcv
Author: chenxf
Author-email: cxf529125853@163.com
Requires-Python: >=3.6
Requires-Dist: numpy
Provides-Extra: cuda
Requires-Dist: pycuda; extra == "cuda"
Dynamic: author
Dynamic: author-email
Dynamic: description
Dynamic: description-content-type
Dynamic: home-page
Dynamic: provides-extra
Dynamic: requires-dist
Dynamic: requires-python
